benchmark_service_sdk/__init__.py
benchmark_service_sdk/client/__init__.py
benchmark_service_sdk/client/client.py
benchmark_service_sdk/client/job_client.py
benchmark_service_sdk/client/model_client.py
benchmark_service_sdk/client/prediction_client.py
benchmark_service_sdk/models/__init__.py
benchmark_service_sdk/models/data_class_base.py
benchmark_service_sdk/models/model_models.py
benchmark_service_sdk/models/prediction_models.py
benchmark_service_sdk/models/task_models.py
benchmark_service_sdk/models/track_models.py
benchmark_service_sdk/models/utils.py
test/__init__.py
test/test_model.py
benchmark_service_sdk-0.1.0.dist-info/LICENSE
benchmark_service_sdk-0.1.0.dist-info/METADATA
benchmark_service_sdk-0.1.0.dist-info/WHEEL
benchmark_service_sdk-0.1.0.dist-info/top_level.txt
benchmark_service_sdk-0.1.0.dist-info/RECORD
