Metadata-Version: 2.1
Name: benchmark-service-sdk
Version: 0.1.0
Summary: A SDK for vision benchmark service.
Home-page: https://github.com/microsoft/benchmark-service-sdk
Author: Xingchao Peng, Ping Jin, Shohei Ono
License: MIT
Requires-Python: >=3.8
License-File: LICENSE
Requires-Dist: requests
